LICENSE
README.rst
setup.py
pdfhextract/__init__.py
pdfhextract/core.py
pdfhextractor.egg-info/PKG-INFO
pdfhextractor.egg-info/SOURCES.txt
pdfhextractor.egg-info/dependency_links.txt
pdfhextractor.egg-info/entry_points.txt
pdfhextractor.egg-info/requires.txt
pdfhextractor.egg-info/top_level.txt