Metadata-Version: 2.1
Name: pdfhextractor
Version: 0.0.2
Summary: An application that extracts highlights from pdfs as markdown files
Home-page: https://github.com/dhingratul/pdf-highlights-extractor
Author: Atul Dhingra
Author-email: dhingratul92@gmail.com
License: Apache-2.0
Platform: UNKNOWN
Classifier: Development Status :: 3 - Alpha
Classifier: Intended Audience :: Developers
Classifier: License :: OSI Approved :: Apache Software License
Classifier: Programming Language :: Python :: 3.8
Classifier: Programming Language :: Python :: 3.9
Classifier: Programming Language :: Python :: 3.10
Classifier: Programming Language :: Python :: 3.11
Classifier: Topic :: Scientific/Engineering :: Information Analysis
Classifier: Topic :: Software Development :: Libraries :: Python Modules
Classifier: Topic :: Utilities
License-File: LICENSE
